todoist_templates/__init__.py
todoist_templates/api.py
todoist_templates/cli.py
todoist_templates/errors.py
todoist_templates/generator.py
todoist_templates/parsers.py
todoist_templates/validator.py
todoist_templates-0.0.2.dist-info/METADATA
todoist_templates-0.0.2.dist-info/WHEEL
todoist_templates-0.0.2.dist-info/entry_points.txt
todoist_templates-0.0.2.dist-info/top_level.txt
todoist_templates-0.0.2.dist-info/RECORD
