Metadata-Version: 2.1
Name: todoist-templates
Version: 0.0.2
Summary: Create Todoist projects from yaml template files
Home-page: https://github.com/maledorak/todoist-templates
Author: Mariusz Korzekwa
Author-email: maledorak@gmail.com
License: MIT license
Keywords: todoist_templates
Platform: UNKNOWN
Classifier: Development Status :: 2 - Pre-Alpha
Classifier: Intended Audience :: Developers
Classifier: License :: OSI Approved :: MIT License
Classifier: Natural Language :: English
Classifier: Programming Language :: Python :: 3
Classifier: Programming Language :: Python :: 3.5
Classifier: Programming Language :: Python :: 3.6
Classifier: Programming Language :: Python :: 3.7
Classifier: Programming Language :: Python :: 3.8
Requires-Python: >=3.5
Requires-Dist: PyYAML (>=5.3.1)
Requires-Dist: todoist-python (>=8.1.1)
